VSVNApplicationMonitoring/__init__.py
VSVNApplicationMonitoring/run.py
VSVNApplicationMonitoring-0.1.4.dist-info/LICENSE
VSVNApplicationMonitoring-0.1.4.dist-info/METADATA
VSVNApplicationMonitoring-0.1.4.dist-info/WHEEL
VSVNApplicationMonitoring-0.1.4.dist-info/top_level.txt
VSVNApplicationMonitoring-0.1.4.dist-info/RECORD
