Metadata-Version: 2.1
Name: VSVNApplicationMonitoring
Version: 0.1.4
Summary: Used for integration with Application monitoring systems
License-File: LICENSE
